{
  "_format": "hh-sol-cache-2",
  "files": {
    "/Users/usultan/Downloads/myCarContract/contracts/myCarContract.sol": {
      "lastModificationDate": 1680779560000,
      "contentHash": "2faace02a93f7bf49d1f6cbe5b405db3",
      "sourceName": "contracts/myCarContract.sol",
      "solcConfig": {
        "version": "0.7.3",
        "settings": {
          "optimizer": {
            "enabled": false,
            "runs": 200
          },
          "outputSelection": {
            "*": {
              "*": [
                "abi",
                "evm.bytecode",
                "evm.deployedBytecode",
                "evm.methodIdentifiers",
                "metadata"
              ],
              "": [
                "ast"
              ]
            }
          }
        }
      },
      "imports": [],
      "versionPragmas": [
        ">=0.7.3"
      ],
      "artifacts": [
        "MyCarContract"
      ]
    }
  }
}
